{
  "url": "https://www.dior.com/ko_kr/fashion/products/2ICBH096IDC_H08G",
  "detail": {
    "description": "컴팩트하고 세련된 반지갑입니다. 그리 플란넬 그레이(Gris Flanelle) 컬러의 그레인 카프스킨 소재로 제작되었으며 앞면의 CD 아이콘 시그니처가 돋보입니다. 내부에 더블 지폐 수납공간, 영수증 수납용 슬립 포켓 2개, 카드 슬롯 8개가 마련되어 있습니다. 포켓 또는 가방 안에 손쉽게 휴대하기 좋습니다.",
    "sizes": "11 x 10 x 1.5cm",
    "material": "카프스킨",
    "colors": "그리 플란넬 그레인 카프스킨",
    "store_inventory": "신세계 강남점 남성, 신세계 부산점 남성, 더 현대 서울, 신세계 본점 남성, 갤러리아 남성, 롯데 본점 남성, 신세계 대전점 남성, 롯데 잠실점 남성, 디올 성수, 하우스 오브 디올, 현대 판교점 남성, 현대 본점 남성 4F"
  }
}